sciwing/__init__.py
sciwing/constants.py
sciwing/api/__init__.py
sciwing/api/api.py
sciwing/api/conf.py
sciwing/api/pdf_store.py
sciwing/api/resources/__init__.py
sciwing/api/resources/parscit_tagger_resource.py
sciwing/api/resources/science_ie_tagger_resource.py
sciwing/api/resources/sect_label_resource.py
sciwing/cli/__init__.py
sciwing/cli/parsect_interact.py
sciwing/cli/s3_mv_cli.py
sciwing/commands/__init__.py
sciwing/commands/develop.py
sciwing/commands/download.py
sciwing/commands/file_gen_utils.py
sciwing/commands/new.py
sciwing/commands/new_dataset.py
sciwing/commands/run.py
sciwing/commands/sciwing_group.py
sciwing/commands/test.py
sciwing/commands/validators.py
sciwing/datasets/__init__.py
sciwing/datasets/sprinkle_dataset.py
sciwing/datasets/classification/__init__.py
sciwing/datasets/classification/base_text_classification.py
sciwing/datasets/classification/generic_sect_dataset.py
sciwing/datasets/classification/sectlabel_dataset.py
sciwing/datasets/seq_labeling/__init__.py
sciwing/datasets/seq_labeling/base_seq_labeling.py
sciwing/datasets/seq_labeling/parscit_dataset.py
sciwing/datasets/seq_labeling/science_ie_dataset.py
sciwing/engine/__init__.py
sciwing/engine/engine.py
sciwing/infer/__init__.py
sciwing/infer/bi_lstm_lc_infer_gensect.py
sciwing/infer/bi_lstm_lc_infer_parsect.py
sciwing/infer/bilstm_crf_infer.py
sciwing/infer/bow_bert_emb_lc_gensect_infer.py
sciwing/infer/bow_bert_emb_lc_parsect_infer.py
sciwing/infer/bow_elmo_emb_lc_gensect_infer.py
sciwing/infer/bow_elmo_emb_lc_parsect_infer.py
sciwing/infer/bow_lc_gensect_infer.py
sciwing/infer/bow_lc_parsect_infer.py
sciwing/infer/elmo_bi_lstm_lc_infer.py
sciwing/infer/science_ie_infer.py
sciwing/infer/classification/BaseClassificationInference.py
sciwing/infer/classification/__init__.py
sciwing/infer/classification/classification_inference.py
sciwing/infer/seq_label_inference/BaseSeqLabelInference.py
sciwing/infer/seq_label_inference/__init__.py
sciwing-0.1.0.dev0.dist-info/LICENSE
sciwing-0.1.0.dev0.dist-info/METADATA
sciwing-0.1.0.dev0.dist-info/WHEEL
sciwing-0.1.0.dev0.dist-info/entry_points.txt
sciwing-0.1.0.dev0.dist-info/top_level.txt
sciwing-0.1.0.dev0.dist-info/RECORD
