Metadata-Version: 2.1
Name: sciwing
Version: 0.1.0.dev0
Summary: Modern Scientific Document Processing Framework 
Home-page: https://github.com/abhinavkashyap/sciwing
Author: abhinav
Author-email: abhinav@comp.nus.edu.sg
License: UNKNOWN
Platform: UNKNOWN
Requires-Dist: networkx
Requires-Dist: wandb
Requires-Dist: logzero
Requires-Dist: falcon-multipart
Requires-Dist: typing
Requires-Dist: torch
Requires-Dist: wasabi
Requires-Dist: boto3
Requires-Dist: tqdm
Requires-Dist: wrapt
Requires-Dist: stopwords
Requires-Dist: allennlp
Requires-Dist: botocore
Requires-Dist: gensim
Requires-Dist: pytorch-pretrained-bert
Requires-Dist: spacy
Requires-Dist: questionary
Requires-Dist: pandas
Requires-Dist: pytorch-crf
Requires-Dist: colorful
Requires-Dist: falcon
Requires-Dist: numpy
Requires-Dist: click
Requires-Dist: toml
Requires-Dist: requests
Requires-Dist: scikit-learn
Requires-Dist: tensorboardX
Requires-Dist: Deprecated
